xbuild/__init__.py
xbuild/__main__.py
xbuild/_builder.py
xbuild/env.py
xbuild-0.2.0.dist-info/licenses/LICENSE
xvenv/__init__.py
xvenv/__main__.py
xvenv/_cross_target.py.tmpl
xvenv/convert.py
xvenv/platforms/__init__.py
xvenv/platforms/android.py
xvenv/platforms/emscripten.py
xvenv/platforms/ios.py
xbuild-0.2.0.dist-info/METADATA
xbuild-0.2.0.dist-info/WHEEL
xbuild-0.2.0.dist-info/entry_points.txt
xbuild-0.2.0.dist-info/top_level.txt
xbuild-0.2.0.dist-info/RECORD
