Metadata-Version: 2.4
Name: xbuild
Version: 0.2.0
Summary: A PEP517 build frontend for cross-compiling wheels.
Author-email: Russell Keith-Magee <russell@keith-magee.com>
Maintainer-email: Russell Keith-Magee <russell@keith-magee.com>
License-Expression: BSD-3-Clause
Project-URL: Project, https://github.com/beeware/xbuild
Project-URL: Funding, https://beeware.org/contributing/membership/
Project-URL: Tracker, https://github.com/beeware/xbuild/issues
Project-URL: Source, https://github.com/beeware/xbuild
Keywords: pep517,build
Classifier: Development Status :: 2 - Pre-Alpha
Classifier: Intended Audience :: Developers
Classifier: Programming Language :: Python :: 3
Classifier: Programming Language :: Python :: 3.13
Classifier: Programming Language :: Python :: 3.14
Classifier: Programming Language :: Python :: 3 :: Only
Classifier: Topic :: Software Development :: Libraries
Classifier: Topic :: System :: Software Distribution
Classifier: Topic :: Software Development
Classifier: Topic :: Utilities
Requires-Python: >=3.13
License-File: LICENSE
Requires-Dist: build==1.3.0
Dynamic: license-file
